lombard/__init__.py
lombard/main.py
tests/__init__.py
tests/conftest.py
tests/test_main.py
tests/test_version.py
lombard-0.0.0.dist-info/LICENSE
lombard-0.0.0.dist-info/METADATA
lombard-0.0.0.dist-info/WHEEL
lombard-0.0.0.dist-info/top_level.txt
lombard-0.0.0.dist-info/RECORD
